pewanalytics/__init__.py
pewanalytics/stats/__init__.py
pewanalytics/stats/clustering.py
pewanalytics/stats/dimensionality_reduction.py
pewanalytics/stats/irr.py
pewanalytics/stats/mutual_info.py
pewanalytics/stats/sampling.py
pewanalytics/text/__init__.py
pewanalytics/text/dates.py
pewanalytics/text/ner.py
pewanalytics/text/topics.py
pewanalytics-1.1.1.dist-info/LICENSE
pewanalytics-1.1.1.dist-info/METADATA
pewanalytics-1.1.1.dist-info/WHEEL
pewanalytics-1.1.1.dist-info/top_level.txt
pewanalytics-1.1.1.dist-info/RECORD
