Metadata-Version: 2.1
Name: pewanalytics
Version: 1.1.1
Summary: Utilities for text processing and statistical analysis from Pew Research Center
Home-page: https://github.com/pewresearch/pewanalytics
Author: Pew Research Center
Author-email: info@pewresearch.org
License: GPLv2+
Keywords: statistics,nlp,text analysis,text processing,sampling,pew pew pew
Platform: UNKNOWN
Classifier: Development Status :: 5 - Production/Stable
Classifier: Environment :: Console
Classifier: Intended Audience :: Developers
Classifier: Intended Audience :: Education
Classifier: Intended Audience :: Information Technology
Classifier: Intended Audience :: Science/Research
Classifier: License :: OSI Approved :: GNU General Public License v2 or later (GPLv2+)
Classifier: Operating System :: OS Independent
Classifier: Programming Language :: Python :: 3.7
Classifier: Programming Language :: Python :: 3.8
Classifier: Programming Language :: Python :: 3.9
Classifier: Programming Language :: Python
Classifier: Topic :: Software Development :: Libraries :: Python Modules
Classifier: Topic :: Utilities
License-File: LICENSE
Requires-Dist: adjustText (>=0.7.3)
Requires-Dist: corextopic (>=1.1)
Requires-Dist: fuzzywuzzy (>=0.17.0)
Requires-Dist: gensim (>=3.8.1)
Requires-Dist: hdbscan (>=0.8.24)
Requires-Dist: matplotlib (>=3.1.2)
Requires-Dist: mca (>=1.0.3)
Requires-Dist: nltk (>=3.4.5)
Requires-Dist: numpy (>=1.18.1)
Requires-Dist: pandas (>=0.25.3)
Requires-Dist: pewtils (>=1.1.1)
Requires-Dist: polyglot (>=16.7.4)
Requires-Dist: python-dateutil (>=2.8.2)
Requires-Dist: rapidfuzz (>=1.5.1)
Requires-Dist: scikit-learn (>=0.24.2)
Requires-Dist: scipy (>=1.4.1)
Requires-Dist: seaborn (>=0.9.0)
Requires-Dist: spacy (>=3.1.2)
Requires-Dist: statsmodels (>=0.10.2)
Requires-Dist: stopit (>=1.1.2)
Requires-Dist: tqdm (>=4.41.1)
